union/__init__.py
union/_async.py
union/_config.py
union/_exceptions.py
union/_interceptor.py
union/_logging.py
union/_testing.py
union/_usage.py
union/_utils.py
union/py.typed
union/_keyring/__init__.py
union/_keyring/file.py
union/_model_loader/__init__.py
union/_model_loader/config.py
union/_model_loader/loader.py
union/_model_loader/shim/__init__.py
union/_model_loader/shim/sglang.py
union/_model_loader/shim/vllm.py
union/_vendor/__init__.py
union/_vendor/isodate/__init__.py
union/actor/__init__.py
union/actor/_actor.py
union/actor/_hash.py
union/app/__init__.py
union/app/_arize.py
union/app/_common.py
union/app/_frameworks.py
union/app/_models.py
union/app/_weave.py
union/app/llm/__init__.py
union/app/llm/_sglang.py
union/app/llm/_vllm.py
union/artifacts/__init__.py
union/artifacts/_artifact.py
union/artifacts/_card.py
union/artifacts/_triggers.py
union/artifacts/_utils.py
union/cache/__init__.py
union/cache/_cache_function_body.py
union/cli/__init__.py
union/cli/_app_common.py
union/cli/_artifact_create_common.py
union/cli/_cache.py
union/cli/_common.py
union/cli/_create.py
union/cli/_delete.py
union/cli/_deploy.py
union/cli/_get.py
union/cli/_info.py
union/cli/_main.py
union/cli/_option.py
union/cli/_start.py
union/cli/_stop.py
union/cli/_update.py
union/configuration/__init__.py
union/configuration/_plugin.py
union/filesystems/__init__.py
union/filesystems/_async_utils.py
union/filesystems/_endpoint.py
union/filesystems/_middleware.py
union/filesystems/_unionfs.py
union/filesystems/_unionmetafs.py
union/internal/__init__.py
union/internal/app/app_definition_pb2.py
union/internal/app/app_definition_pb2.pyi
union/internal/app/app_definition_pb2_grpc.py
union/internal/app/app_logs_payload_pb2.py
union/internal/app/app_logs_payload_pb2.pyi
union/internal/app/app_logs_payload_pb2_grpc.py
union/internal/app/app_logs_service_pb2.py
union/internal/app/app_logs_service_pb2.pyi
union/internal/app/app_logs_service_pb2_grpc.py
union/internal/app/app_payload_pb2.py
union-0.1.193.dist-info/licenses/LICENSE
union-0.1.193.dist-info/licenses/licenses/APL.txt
union-0.1.193.dist-info/licenses/licenses/BSL.txt
union-0.1.193.dist-info/METADATA
union-0.1.193.dist-info/WHEEL
union-0.1.193.dist-info/entry_points.txt
union-0.1.193.dist-info/top_level.txt
union-0.1.193.dist-info/RECORD
